coze_coding_dev_sdk/__init__.py
coze_coding_dev_sdk/cli/__init__.py
coze_coding_dev_sdk/cli/chat.py
coze_coding_dev_sdk/cli/cli.py
coze_coding_dev_sdk/cli/constants.py
coze_coding_dev_sdk/cli/db.py
coze_coding_dev_sdk/cli/embedding.py
coze_coding_dev_sdk/cli/image.py
coze_coding_dev_sdk/cli/knowledge.py
coze_coding_dev_sdk/cli/search.py
coze_coding_dev_sdk/cli/utils.py
coze_coding_dev_sdk/cli/video.py
coze_coding_dev_sdk/cli/video_edit.py
coze_coding_dev_sdk/cli/voice.py
coze_coding_dev_sdk/core/__init__.py
coze_coding_dev_sdk/core/client.py
coze_coding_dev_sdk/core/config.py
coze_coding_dev_sdk/core/exceptions.py
coze_coding_dev_sdk/database/__init__.py
coze_coding_dev_sdk/database/client.py
coze_coding_dev_sdk/database/migration.py
coze_coding_dev_sdk/embedding/__init__.py
coze_coding_dev_sdk/embedding/client.py
coze_coding_dev_sdk/embedding/models.py
coze_coding_dev_sdk/image/__init__.py
coze_coding_dev_sdk/image/client.py
coze_coding_dev_sdk/image/models.py
coze_coding_dev_sdk/knowledge/__init__.py
coze_coding_dev_sdk/knowledge/client.py
coze_coding_dev_sdk/knowledge/models.py
coze_coding_dev_sdk/llm/__init__.py
coze_coding_dev_sdk/llm/client.py
coze_coding_dev_sdk/llm/models.py
coze_coding_dev_sdk/memory/__init__.py
coze_coding_dev_sdk/memory/client.py
coze_coding_dev_sdk/s3/__init__.py
coze_coding_dev_sdk/s3/client.py
coze_coding_dev_sdk/s3/models.py
coze_coding_dev_sdk/search/__init__.py
coze_coding_dev_sdk/search/client.py
coze_coding_dev_sdk/search/models.py
coze_coding_dev_sdk/video/__init__.py
coze_coding_dev_sdk/video/client.py
coze_coding_dev_sdk/video/models.py
coze_coding_dev_sdk/video_edit/__init__.py
coze_coding_dev_sdk/video_edit/examples.py
coze_coding_dev_sdk/video_edit/frame_extractor.py
coze_coding_dev_sdk/video_edit/models.py
coze_coding_dev_sdk/video_edit/video_edit.py
coze_coding_dev_sdk/voice/__init__.py
coze_coding_dev_sdk/voice/asr.py
coze_coding_dev_sdk/voice/models.py
coze_coding_dev_sdk/voice/tts.py
coze_coding_dev_sdk-0.5.7.dist-info/licenses/LICENSE
coze_coding_dev_sdk-0.5.7.dist-info/METADATA
coze_coding_dev_sdk-0.5.7.dist-info/WHEEL
coze_coding_dev_sdk-0.5.7.dist-info/entry_points.txt
coze_coding_dev_sdk-0.5.7.dist-info/top_level.txt
coze_coding_dev_sdk-0.5.7.dist-info/RECORD
