Metadata-Version: 2.4
Name: coze-coding-dev-sdk
Version: 0.5.7
Summary: Coze Coding Dev SDK - 优雅的多功能 AI SDK，支持图片生成、视频生成、语音合成、语音识别、大语言模型、联网搜索和文本/多模态 Embedding。包含命令行工具 coze-coding-ai，支持 Context 上下文追踪
Author-email: Coze Coding Integration Team <support@coze.com>
Maintainer-email: Coze Coding Integration Team <support@coze.com>
License-Expression: MIT
Project-URL: Homepage, https://github.com/coze/coze-coding-dev-sdk
Project-URL: Documentation, https://github.com/coze/coze-coding-dev-sdk#readme
Project-URL: Repository, https://github.com/coze/coze-coding-dev-sdk
Project-URL: Issues, https://github.com/coze/coze-coding-dev-sdk/issues
Project-URL: Changelog, https://github.com/coze/coze-coding-dev-sdk/blob/main/CHANGELOG.md
Keywords: coze,coze-coding,integration,ai,sdk,image-generation,video-generation,text-to-speech,speech-recognition,llm,search,embedding,vector-embedding,semantic-search,rag,doubao,seedream
Classifier: Development Status :: 4 - Beta
Classifier: Intended Audience :: Developers
Classifier: Operating System :: OS Independent
Classifier: Programming Language :: Python :: 3
Classifier: Programming Language :: Python :: 3.11
Classifier: Programming Language :: Python :: 3.12
Classifier: Topic :: Software Development :: Libraries :: Python Modules
Classifier: Topic :: Scientific/Engineering :: Artificial Intelligence
Classifier: Topic :: Multimedia :: Graphics
Classifier: Topic :: Multimedia :: Sound/Audio
Classifier: Topic :: Multimedia :: Video
Requires-Python: >=3.11
License-File: LICENSE
Requires-Dist: requests>=2.31.0
Requires-Dist: pydantic>=2.0.0
Requires-Dist: cozeloop>=0.1.0
Requires-Dist: coze-coding-utils>=0.1.0
Requires-Dist: langchain-openai>=0.1.0
Requires-Dist: langchain-core>=0.1.0
Requires-Dist: sqlalchemy>=2.0.0
Requires-Dist: alembic>=1.13.0
Requires-Dist: sqlacodegen>=3.0.0
Requires-Dist: psycopg[binary]>=3.0.0
Requires-Dist: psycopg-pool>=3.0.0
Requires-Dist: langgraph>=0.2.0
Requires-Dist: langgraph-checkpoint-postgres>=3.0.0
Requires-Dist: boto3>=1.26.0
Requires-Dist: click>=8.0.0
Requires-Dist: rich>=13.0.0
Provides-Extra: dev
Requires-Dist: pytest>=7.0.0; extra == "dev"
Requires-Dist: pytest-asyncio>=0.21.0; extra == "dev"
Requires-Dist: build>=1.0.0; extra == "dev"
Requires-Dist: twine>=4.0.0; extra == "dev"
Dynamic: license-file
